local opcodes = {
    {"MOVE", FORMAT = "ABC"},
    {"LOADI", FORMAT = "AsBx"},
    {"LOADF", FORMAT = "AsBx"},
    {"LOADK", FORMAT = "ABx"},
    {"LOADKX", FORMAT = "ABx"},
    {"LOADFALSE", FORMAT = "ABC"},
    {"LFALSESKIP", FORMAT = "ABC"},
    {"LOADTRUE", FORMAT = "ABC"},
    {"LOADNIL", FORMAT = "ABC"},
    {"GETUPVAL", FORMAT = "ABC"},
    {"SETUPVAL", FORMAT = "ABC"},
    {"GETTABUP", FORMAT = "ABC"},
    {"GETTABLE", FORMAT = "ABC"},
    {"GETI", FORMAT = "ABC"},
    {"GETFIELD", FORMAT = "ABC"},
    {"SETTABUP", FORMAT = "ABC"},
    {"SETTABLE", FORMAT = "ABC"},
    {"SETI", FORMAT = "ABC"},
    {"SETFIELD", FORMAT = "ABC"},
    {"NEWTABLE", FORMAT = "ABC"},
    {"SELF", FORMAT = "ABC"},
    {"ADDI", FORMAT = "ABC"},
    {"ADDK", FORMAT = "ABC"},
    {"SUBK", FORMAT = "ABC"},
    {"MULK", FORMAT = "ABC"},
    {"MODK", FORMAT = "ABC"},
    {"POWK", FORMAT = "ABC"},
    {"DIVK", FORMAT = "ABC"},
    {"IDIVK", FORMAT = "ABC"},
    {"BANDK", FORMAT = "ABC"},
    {"BORK", FORMAT = "ABC"},
    {"BXORK", FORMAT = "ABC"},
    {"SHRI", FORMAT = "ABC"},
    {"SHLI", FORMAT = "ABC"},
    {"ADD", FORMAT = "ABC"},
    {"SUB", FORMAT = "ABC"},
    {"MUL", FORMAT = "ABC"},
    {"MOD", FORMAT = "ABC"},
    {"POW", FORMAT = "ABC"},
    {"DIV", FORMAT = "ABC"},
    {"IDIV", FORMAT = "ABC"},
    {"BAND", FORMAT = "ABC"},
    {"BOR", FORMAT = "ABC"},
    {"BXOR", FORMAT = "ABC"},
    {"SHL", FORMAT = "ABC"},
    {"SHR", FORMAT = "ABC"},
    {"MMBIN", FORMAT = "ABC"},
    {"MMBINI", FORMAT = "ABC"},
    {"MMBINK", FORMAT = "ABC"},
    {"UNM", FORMAT = "ABC"},
    {"BNOT", FORMAT = "ABC"},
    {"NOT", FORMAT = "ABC"},
    {"LEN", FORMAT = "ABC"},
    {"CONCAT", FORMAT = "ABC"},
    {"CLOSE", FORMAT = "ABC"},
    {"TBC", FORMAT = "ABC"},
    {"JMP", FORMAT = "sJ"},
    {"EQ", FORMAT = "ABC"},
    {"LT", FORMAT = "ABC"},
    {"LE", FORMAT = "ABC"},
    {"EQK", FORMAT = "ABC"},
    {"EQI", FORMAT = "ABC"},
    {"LTI", FORMAT = "ABC"},
    {"LEI", FORMAT = "ABC"},
    {"GTI", FORMAT = "ABC"},
    {"GEI", FORMAT = "ABC"},
    {"TEST", FORMAT = "ABC"},
    {"TESTSET", FORMAT = "ABC"},
    {"CALL", FORMAT = "ABC"},
    {"TAILCALL", FORMAT = "ABC"},
    {"RETURN", FORMAT = "ABC"},
    {"RETURN0", FORMAT = "ABC"},
    {"RETURN1", FORMAT = "ABC"},
    {"FORLOOP", FORMAT = "ABx"},
    {"FORPREP", FORMAT = "ABx"},
    {"TFORPREP", FORMAT = "ABx"},
    {"TFORCALL", FORMAT = "ABC"},
    {"TFORLOOP", FORMAT = "ABx"},
    {"SETLIST", FORMAT = "ABC"},
    {"CLOSURE", FORMAT = "ABx"},
    {"VARARG", FORMAT = "ABC"},
    {"VARARGPREP", FORMAT = "ABC"},
    {"EXTRAARG", FORMAT = "Ax"},
    {"SUPER", FORMAT = "???"}
};

for key = 0, #opcodes do
    opcodes[key] = opcodes[key + 1]
end

return opcodes